[
    {
        "key": 0,
        "word": "Մարս"
    },
    {
        "key": 1,
        "word": "ջունգլի"
    },
    {
        "key": 2,
        "word": "Յուպիտեր"
    },
    {
        "key": 3,
        "word": "Լուսին"
    },
    {
        "key": 4,
        "word": "ԱՄՆ"
    },
    {
        "key": 5,
        "word": "Ֆրանսիա"
    },
    {
        "key": 6,
        "word": "Ռուսաստան"
    },
    {
        "key": 7,
        "word": "Իրան"
    },
    {
        "key": 8,
        "word": "հիվանդանոց"
    },
    {
        "key": 9,
        "word": "Սահարա անապատ"
    },
    {
        "key": 10,
        "word": "թանգարան"
    },
    {
        "key": 11,
        "word": "սառցադաշտ"
    },
    {
        "key": 12,
        "word": "ծով"
    },
    {
        "key": 13,
        "word": "կինոստուդիա"
    },
    {
        "key": 14,
        "word": "թատրոն"
    },
    {
        "key": 15,
        "word": "համերգասրահ"
    },
    {
        "key": 16,
        "word": "թեյարան"
    },
    {
        "key": 17,
        "word": "սրճարան"
    },
    {
        "key": 18,
        "word": "լվացքատուն"
    },
    {
        "key": 19,
        "word": "զբոսայգի"
    },
    {
        "key": 20,
        "word": "բուսաբանական այգի"
    },
    {
        "key": 21,
        "word": "կենդանաբանական այգի"
    },
    {
        "key": 22,
        "word": "բանկ"
    },
    {
        "key": 23,
        "word": "գրախանութ"
    },
    {
        "key": 24,
        "word": "պահարան"
    },
    {
        "key": 25,
        "word": "գրապահարան"
    },
    {
        "key": 26,
        "word": "ուսուցչանոց"
    },
    {
        "key": 27,
        "word": "ծաղկանոց"
    },
    {
        "key": 28,
        "word": "ջերմոց"
    },
    {
        "key": 29,
        "word": "համալսարան"
    },
    {
        "key": 30,
        "word": "տեխնիկայի խանութ"
    },
    {
        "key": 31,
        "word": "ձայնագրման ստուդիա"
    },
    {
        "key": 32,
        "word": "զիփլայն"
    },
    {
        "key": 33,
        "word": "օդանավակայան"
    },
    {
        "key": 34,
        "word": "դպրոց"
    },
    {
        "key": 35,
        "word": "մետրո"
    },
    {
        "key": 36,
        "word": "խաղատուն"
    },
    {
        "key": 37,
        "word": "գրադարան"
    },
    {
        "key": 38,
        "word": "դարբնոց"
    },
    {
        "key": 39,
        "word": "ծերանոց"
    },
    {
        "key": 40,
        "word": "այգի"
    },
    {
        "key": 41,
        "word": "Իտալիա"
    },
    {
        "key": 42,
        "word": "Հայաստան"
    },
    {
        "key": 43,
        "word": "Չինաստան"
    },
    {
        "key": 44,
        "word": "Ասիա"
    },
    {
        "key": 45,
        "word": "Եվրոպա"
    },
    {
        "key": 46,
        "word": "Հունաստան"
    },
    {
        "key": 47,
        "word": "Ավստրալիա"
    },
    {
        "key": 48,
        "word": "օվկիանոս"
    },
    {
        "key": 49,
        "word": "գետ"
    },
    {
        "key": 50,
        "word": "Կանադա"
    },
    {
        "key": 51,
        "word": "ճաշարան"
    },
    {
        "key": 52,
        "word": "լսարան"
    },
    {
        "key": 53,
        "word": "փողոց"
    },
    {
        "key": 54,
        "word": "մանկապարտեզ"
    },
    {
        "key": 55,
        "word": "մարզադաշտ"
    },
    {
        "key": 56,
        "word": "սահադաշտ"
    },
    {
        "key": 57,
        "word": "խաղադաշտ"
    },
    {
        "key": 58,
        "word": "Լաստիվեր"
    },
    {
        "key": 59,
        "word": "Արգենտինա"
    },
    {
        "key": 60,
        "word": "Բրազիլիա"
    },
    {
        "key": 61,
        "word": "Իսպանիա"
    },
    {
        "key": 62,
        "word": "Եգիպտոս"
    },
    {
        "key": 63,
        "word": "Կարմիր ծով"
    },
    {
        "key": 64,
        "word": "Սև ծով"
    },
    {
        "key": 65,
        "word": "Միջերկրական ծով"
    },
    {
        "key": 66,
        "word": "Ատլանտյան օվկիանոս"
    },
    {
        "key": 67,
        "word": "Խաղաղ օվկիանոս"
    },
    {
        "key": 68,
        "word": "Հնդկական օվկիանոս"
    },
    {
        "key": 69,
        "word": "Հյուսիսային օվկիանոս"
    },
    {
        "key": 70,
        "word": "հանդերձարան"
    },
    {
        "key": 71,
        "word": "պահեստ"
    },
    {
        "key": 72,
        "word": "քվեստ"
    },
    {
        "key": 73,
        "word": "օպերա"
    },
    {
        "key": 74,
        "word": "էյֆելյան աշտարակ"
    },
    {
        "key": 75,
        "word": "Պիզայի աշտարակ"
    },
    {
        "key": 76,
        "word": "Կոլիզեում"
    },
    {
        "key": 77,
        "word": "Քեոփսի բուրգ"
    },
    {
        "key": 78,
        "word": "Ազատության արձան"
    },
    {
        "key": 79,
        "word": "Կրեմլ"
    },
    {
        "key": 80,
        "word": "Բեռլինի պատ"
    },
    {
        "key": 81,
        "word": "Բիգ Բեն"
    },
    {
        "key": 82,
        "word": "Լուվրի թանգարան"
    },
    {
        "key": 83,
        "word": "Անկտարտիդա"
    },
    {
        "key": 84,
        "word": "Աֆրիկա"
    },
    {
        "key": 85,
        "word": "անապատ"
    },
    {
        "key": 86,
        "word": "Մերկուրի"
    },
    {
        "key": 87,
        "word": "Բերմուդյան եռանկյունի"
    },
    {
        "key": 88,
        "word": "Ռիո դե Ժանեյրո"
    },
    {
        "key": 89,
        "word": "Մոսկվա"
    }
]